bumpfontversion/__init__.py
bumpfontversion/__main__.py
bumpfontversion/glyphshandler.py
bumpfontversion/sfnthandler.py
bumpfontversion/ufohandler.py
bumpfontversion-0.4.0.dist-info/entry_points.txt
bumpfontversion-0.4.0.dist-info/WHEEL
bumpfontversion-0.4.0.dist-info/METADATA
bumpfontversion-0.4.0.dist-info/RECORD
