Metadata-Version: 2.1
Name: bumpfontversion
Version: 0.4.0
Summary: Bumps the version of a font source file
License: Apache
Author: Simon Cozens
Author-email: simon@simon-cozens.org
Requires-Python: >=3.7,<4.0
Classifier: License :: Other/Proprietary License
Classifier: Programming Language :: Python :: 3
Classifier: Programming Language :: Python :: 3.7
Classifier: Programming Language :: Python :: 3.8
Classifier: Programming Language :: Python :: 3.9
Requires-Dist: bump2version (==1.0.1)
Requires-Dist: fontTools
Requires-Dist: glyphsLib (==6.0.0b4)
Requires-Dist: openstep-plist
Requires-Dist: ufoLib2
